Metadata-Version: 2.1
Name: lorax
Version: 0.94.82
Summary: lorax -- speaks for the (phylogenetic) trees.
Home-page: http://github.com/LegumeFederation/lorax
Author: Joel Berendzen
Author-email: joelb@ncgr.org
Maintainer: Joel Berendzen
Maintainer-email: joelb@ncgr.org
License: BSD 3-Clause License
Keywords: science,biology,bioinformatics,genomics,phylogeny,genes,gene families,multiple sequence alignment,phylogenetic trees
Platform: UNKNOWN
Classifier: Development Status :: 4 - Beta
Classifier: Environment :: Console
Classifier: Framework :: Flask
Classifier: Intended Audience :: Science/Research
Classifier: License :: OSI Approved :: BSD License
Classifier: Operating System :: MacOS :: MacOS X
Classifier: Operating System :: POSIX :: Linux
Classifier: Operating System :: POSIX :: BSD
Classifier: Programming Language :: Python :: 3.4
Classifier: Programming Language :: Python :: 3.5
Classifier: Programming Language :: Python :: 3.6
Classifier: Programming Language :: C
Classifier: Topic :: Scientific/Engineering :: Bio-Informatics
Classifier: Topic :: Internet :: WWW/HTTP :: WSGI :: Server
Provides-Extra: tests
Provides-Extra: docs
Provides-Extra: all
